{
    "type": "FeatureCollection",
    "name": "Southwaikato_Urban_2025-26 - Imagery_Centres",
    "crs": {
        "type": "name",
        "properties": {
            "name": "urn:ogc:def:crs:OGC:1.3:CRS84"
        }
    },
    "xy_coordinate_resolution": 1e-15,
    "features": [
        {
            "type": "Feature",
            "properties": {
                "Project": "PGRM3302",
                "Proj_Name": "South Waikato Urban Imagery 2025-26",
                "Survey_Typ": "Imagery",
                "OrthoGSD_m": 10.0
            },
            "geometry": {
                "type": "Point",
                "coordinates": [
                    175.806485090976651,
                    -38.132222103775945
                ]
            }
        }
    ]
}